pagedown/__init__.py
pagedown/apps.py
pagedown/forms.py
pagedown/models.py
pagedown/settings.py
pagedown/tests.py
pagedown/urls.py
pagedown/utils.py
pagedown/views.py
pagedown/widgets.py
pagedown/static/pagedown.css
pagedown/static/pagedown_init.js
pagedown/static/admin/css/pagedown.css
pagedown/static/admin/js/pagedown.js
pagedown/static/pagedown/LICENSE.txt
pagedown/static/pagedown/Markdown.Converter.js
pagedown/static/pagedown/Markdown.Editor.js
pagedown/static/pagedown/Markdown.Sanitizer.js
pagedown/static/pagedown/README.txt
pagedown/static/pagedown/node-pagedown.js
pagedown/static/pagedown/wmd-buttons.png
pagedown/static/pagedown/demo/browser/demo.css
pagedown/static/pagedown/demo/browser/demo.html
pagedown/static/pagedown/demo/node/demo.js
pagedown/static/pagedown/local/Markdown.local.fr.js
pagedown/static/pagedown-extra/Markdown.Extra.js
pagedown/static/pagedown-extra/pagedown/Markdown.Converter.js
pagedown/templates/pagedown/forms/widgets/attrs.html
pagedown/templates/pagedown/forms/widgets/default.html
pagedown/templates/pagedown/forms/widgets/textarea.html
pagedown/templates/pagedown/widgets/default.html
django_pagedown-2.2.1.dist-info/LICENSE.txt
django_pagedown-2.2.1.dist-info/METADATA
django_pagedown-2.2.1.dist-info/WHEEL
django_pagedown-2.2.1.dist-info/top_level.txt
django_pagedown-2.2.1.dist-info/RECORD
